{"levelName":"col 72","levelID":2,"version":1,"difficulty":5.5,"dateCreated":"6/12/2018 7:32:04 PM","dateModified":"6/12/2018 7:32:42 PM","slots":[{"number":6,"hideNumber":true,"hexPosition":{"col":4,"row":1},"position":{"x":4.0,"y":-5.0,"z":1.0}},{"number":6,"hideNumber":true,"hexPosition":{"col":5,"row":1},"position":{"x":5.0,"y":-6.0,"z":1.0}},{"number":0,"hideNumber":false,"hexPosition":{"col":3,"row":2},"position":{"x":3.0,"y":-5.0,"z":2.0}},{"number":7,"hideNumber":false,"hexPosition":{"col":4,"row":2},"position":{"x":4.0,"y":-6.0,"z":2.0}},{"number":0,"hideNumber":false,"hexPosition":{"col":5,"row":2},"position":{"x":5.0,"y":-7.0,"z":2.0}},{"number":6,"hideNumber":false,"hexPosition":{"col":3,"row":3},"position":{"x":3.0,"y":-6.0,"z":3.0}},{"number":6,"hideNumber":true,"hexPosition":{"col":4,"row":3},"position":{"x":4.0,"y":-7.0,"z":3.0}}],"solution":{"bestScore":44,"twoStarScore":43,"worstScore":43,"numSolutions":12,"numBestSolutions":4,"bestPath":[{"x":4.0,"y":-6.0,"z":2.0},{"x":5.0,"y":-7.0,"z":2.0},{"x":5.0,"y":-6.0,"z":1.0},{"x":4.0,"y":-5.0,"z":1.0},{"x":3.0,"y":-5.0,"z":2.0},{"x":3.0,"y":-6.0,"z":3.0},{"x":4.0,"y":-7.0,"z":3.0}],"version":1}}