{"levelName":"col 69","levelID":260,"version":1,"difficulty":1.100000023841858,"dateCreated":"6/12/2018 7:23:04 PM","dateModified":"6/12/2018 7:25:51 PM","slots":[{"number":0,"hideNumber":false,"hexPosition":{"col":4,"row":1},"position":{"x":4.0,"y":-5.0,"z":1.0}},{"number":0,"hideNumber":false,"hexPosition":{"col":5,"row":1},"position":{"x":5.0,"y":-6.0,"z":1.0}},{"number":0,"hideNumber":false,"hexPosition":{"col":7,"row":1},"position":{"x":7.0,"y":-8.0,"z":1.0}},{"number":0,"hideNumber":false,"hexPosition":{"col":3,"row":2},"position":{"x":3.0,"y":-5.0,"z":2.0}},{"number":4,"hideNumber":false,"hexPosition":{"col":4,"row":2},"position":{"x":4.0,"y":-6.0,"z":2.0}},{"number":0,"hideNumber":false,"hexPosition":{"col":5,"row":2},"position":{"x":5.0,"y":-7.0,"z":2.0}},{"number":4,"hideNumber":true,"hexPosition":{"col":6,"row":2},"position":{"x":6.0,"y":-8.0,"z":2.0}},{"number":0,"hideNumber":false,"hexPosition":{"col":7,"row":2},"position":{"x":7.0,"y":-9.0,"z":2.0}},{"number":0,"hideNumber":false,"hexPosition":{"col":2,"row":3},"position":{"x":2.0,"y":-5.0,"z":3.0}},{"number":0,"hideNumber":false,"hexPosition":{"col":3,"row":3},"position":{"x":3.0,"y":-6.0,"z":3.0}},{"number":0,"hideNumber":false,"hexPosition":{"col":4,"row":3},"position":{"x":4.0,"y":-7.0,"z":3.0}},{"number":0,"hideNumber":false,"hexPosition":{"col":5,"row":3},"position":{"x":5.0,"y":-8.0,"z":3.0}},{"number":0,"hideNumber":false,"hexPosition":{"col":6,"row":3},"position":{"x":6.0,"y":-9.0,"z":3.0}},{"number":0,"hideNumber":false,"hexPosition":{"col":1,"row":4},"position":{"x":1.0,"y":-5.0,"z":4.0}},{"number":4,"hideNumber":true,"hexPosition":{"col":2,"row":4},"position":{"x":2.0,"y":-6.0,"z":4.0}},{"number":0,"hideNumber":false,"hexPosition":{"col":3,"row":4},"position":{"x":3.0,"y":-7.0,"z":4.0}},{"number":0,"hideNumber":false,"hexPosition":{"col":1,"row":5},"position":{"x":1.0,"y":-6.0,"z":5.0}}],"solution":{"bestScore":68,"twoStarScore":68,"worstScore":68,"numSolutions":394,"numBestSolutions":394,"bestPath":[{"x":4.0,"y":-6.0,"z":2.0},{"x":4.0,"y":-5.0,"z":1.0},{"x":5.0,"y":-6.0,"z":1.0},{"x":5.0,"y":-7.0,"z":2.0},{"x":6.0,"y":-8.0,"z":2.0},{"x":7.0,"y":-8.0,"z":1.0},{"x":7.0,"y":-9.0,"z":2.0},{"x":6.0,"y":-9.0,"z":3.0},{"x":5.0,"y":-8.0,"z":3.0},{"x":4.0,"y":-7.0,"z":3.0},{"x":3.0,"y":-7.0,"z":4.0},{"x":3.0,"y":-6.0,"z":3.0},{"x":3.0,"y":-5.0,"z":2.0},{"x":2.0,"y":-5.0,"z":3.0},{"x":2.0,"y":-6.0,"z":4.0},{"x":1.0,"y":-6.0,"z":5.0},{"x":1.0,"y":-5.0,"z":4.0}],"version":1}}