{"levelName":"col 50","levelID":17,"version":3,"difficulty":5.75,"dateCreated":"6/12/2018 5:34:18 PM","dateModified":"7/24/2018 8:25:02 PM","slots":[{"number":0,"hideNumber":false,"hexPosition":{"col":3,"row":3},"position":{"x":3.0,"y":-6.0,"z":3.0}},{"number":8,"hideNumber":false,"hexPosition":{"col":4,"row":3},"position":{"x":4.0,"y":-7.0,"z":3.0}},{"number":0,"hideNumber":false,"hexPosition":{"col":2,"row":4},"position":{"x":2.0,"y":-6.0,"z":4.0}},{"number":0,"hideNumber":false,"hexPosition":{"col":3,"row":4},"position":{"x":3.0,"y":-7.0,"z":4.0}},{"number":8,"hideNumber":true,"hexPosition":{"col":3,"row":1},"position":{"x":3.0,"y":-4.0,"z":1.0}},{"number":0,"hideNumber":false,"hexPosition":{"col":4,"row":1},"position":{"x":4.0,"y":-5.0,"z":1.0}},{"number":0,"hideNumber":false,"hexPosition":{"col":5,"row":1},"position":{"x":5.0,"y":-6.0,"z":1.0}},{"number":8,"hideNumber":false,"hexPosition":{"col":2,"row":2},"position":{"x":2.0,"y":-4.0,"z":2.0}},{"number":0,"hideNumber":false,"hexPosition":{"col":4,"row":2},"position":{"x":4.0,"y":-6.0,"z":2.0}},{"number":0,"hideNumber":false,"hexPosition":{"col":5,"row":2},"position":{"x":5.0,"y":-7.0,"z":2.0}},{"number":8,"hideNumber":true,"hexPosition":{"col":1,"row":3},"position":{"x":1.0,"y":-4.0,"z":3.0}},{"number":0,"hideNumber":false,"hexPosition":{"col":5,"row":3},"position":{"x":5.0,"y":-8.0,"z":3.0}},{"number":0,"hideNumber":false,"hexPosition":{"col":1,"row":4},"position":{"x":1.0,"y":-5.0,"z":4.0}},{"number":0,"hideNumber":false,"hexPosition":{"col":5,"row":4},"position":{"x":5.0,"y":-9.0,"z":4.0}},{"number":0,"hideNumber":false,"hexPosition":{"col":3,"row":5},"position":{"x":3.0,"y":-8.0,"z":5.0}},{"number":0,"hideNumber":false,"hexPosition":{"col":4,"row":5},"position":{"x":4.0,"y":-9.0,"z":5.0}},{"number":9,"hideNumber":false,"hexPosition":{"col":6,"row":0},"position":{"x":6.0,"y":-6.0,"z":0.0}},{"number":9,"hideNumber":true,"hexPosition":{"col":6,"row":1},"position":{"x":6.0,"y":-7.0,"z":1.0}},{"number":9,"hideNumber":true,"hexPosition":{"col":6,"row":2},"position":{"x":6.0,"y":-8.0,"z":2.0}},{"number":9,"hideNumber":false,"hexPosition":{"col":2,"row":5},"position":{"x":2.0,"y":-7.0,"z":5.0}}],"solution":{"bestScore":174,"twoStarScore":171,"worstScore":169,"numSolutions":334,"numBestSolutions":6,"bestPath":[{"x":6.0,"y":-6.0,"z":0.0},{"x":6.0,"y":-7.0,"z":1.0},{"x":5.0,"y":-6.0,"z":1.0},{"x":5.0,"y":-7.0,"z":2.0},{"x":6.0,"y":-8.0,"z":2.0},{"x":5.0,"y":-8.0,"z":3.0},{"x":5.0,"y":-9.0,"z":4.0},{"x":4.0,"y":-9.0,"z":5.0},{"x":3.0,"y":-8.0,"z":5.0},{"x":2.0,"y":-7.0,"z":5.0},{"x":3.0,"y":-7.0,"z":4.0},{"x":3.0,"y":-6.0,"z":3.0},{"x":2.0,"y":-6.0,"z":4.0},{"x":1.0,"y":-5.0,"z":4.0},{"x":1.0,"y":-4.0,"z":3.0},{"x":2.0,"y":-4.0,"z":2.0},{"x":3.0,"y":-4.0,"z":1.0},{"x":4.0,"y":-5.0,"z":1.0},{"x":4.0,"y":-6.0,"z":2.0},{"x":4.0,"y":-7.0,"z":3.0}],"version":3}}