{"levelName":"ez 74","levelID":40,"version":2,"difficulty":1.5,"dateCreated":"4/12/2018 10:10:34 PM","dateModified":"4/12/2018 10:12:05 PM","slots":[{"number":0,"hideNumber":false,"hexPosition":{"col":4,"row":1},"position":{"x":4.0,"y":-5.0,"z":1.0}},{"number":1,"hideNumber":true,"hexPosition":{"col":5,"row":1},"position":{"x":5.0,"y":-6.0,"z":1.0}},{"number":1,"hideNumber":true,"hexPosition":{"col":3,"row":2},"position":{"x":3.0,"y":-5.0,"z":2.0}},{"number":9,"hideNumber":false,"hexPosition":{"col":4,"row":2},"position":{"x":4.0,"y":-6.0,"z":2.0}},{"number":0,"hideNumber":false,"hexPosition":{"col":5,"row":2},"position":{"x":5.0,"y":-7.0,"z":2.0}},{"number":0,"hideNumber":false,"hexPosition":{"col":3,"row":3},"position":{"x":3.0,"y":-6.0,"z":3.0}},{"number":1,"hideNumber":false,"hexPosition":{"col":4,"row":3},"position":{"x":4.0,"y":-7.0,"z":3.0}},{"number":9,"hideNumber":true,"hexPosition":{"col":5,"row":3},"position":{"x":5.0,"y":-8.0,"z":3.0}},{"number":9,"hideNumber":true,"hexPosition":{"col":3,"row":4},"position":{"x":3.0,"y":-7.0,"z":4.0}},{"number":0,"hideNumber":false,"hexPosition":{"col":4,"row":4},"position":{"x":4.0,"y":-8.0,"z":4.0}}],"solution":{"bestScore":50,"twoStarScore":50,"worstScore":50,"numSolutions":6,"numBestSolutions":6,"bestPath":[{"x":4.0,"y":-6.0,"z":2.0},{"x":5.0,"y":-7.0,"z":2.0},{"x":5.0,"y":-8.0,"z":3.0},{"x":4.0,"y":-8.0,"z":4.0},{"x":3.0,"y":-7.0,"z":4.0},{"x":4.0,"y":-7.0,"z":3.0},{"x":3.0,"y":-6.0,"z":3.0},{"x":3.0,"y":-5.0,"z":2.0},{"x":4.0,"y":-5.0,"z":1.0},{"x":5.0,"y":-6.0,"z":1.0}],"version":2}}